[
    {
        "type": "skill",
        "id": "mining",
        "sort": 0
    },
    {
        "type": "skill",
        "id": "woodcutting",
        "sort": 1
    },
    {
        "type": "skill",
        "id": "foraging",
        "sort": 2
    },
    {
        "type": "skill",
        "id": "smithing",
        "sort": 3
    },
    {
        "type": "skill",
        "id": "crafting",
        "sort": 4
    },
    {
        "type": "skill",
        "id": "tailoring",
        "sort": 5
    },
    {
        "type": "skill",
        "id": "cooking",
        "sort": 6
    },
    {
        "type": "skill",
        "id": "brewing",
        "sort": 7
    },
    {
        "type": "skill",
        "id": "alchemy",
        "sort": 8
    },
    {
        "type": "skill",
        "id": "enhancing",
        "sort": 9
    },
    {
        "type": "skill",
        "id": "intelligence",
        "sort": 10
    },
    {
        "type": "skill",
        "id": "stamina",
        "sort": 11
    },
    {
        "type": "skill",
        "id": "defense",
        "sort": 12
    },
    {
        "type": "skill",
        "id": "melee",
        "sort": 14
    },
    {
        "type": "skill",
        "id": "ranged",
        "sort": 15
    },
    {
        "type": "skill",
        "id": "magic",
        "sort": 16
    },
    {
        "type": "state",
        "id": "miningSpeed",
        "base": 0
    },
    {
        "type": "state",
        "id": "woodcuttingSpeed",
        "base": 0
    },
    {
        "type": "state",
        "id": "foragingSpeed",
        "base": 0
    },
    {
        "type": "state",
        "id": "smithingSpeed",
        "base": 0
    },
    {
        "type": "state",
        "id": "craftingSpeed",
        "base": 0
    },
    {
        "type": "state",
        "id": "tailoringSpeed",
        "base": 0
    },
    {
        "type": "state",
        "id": "cookingSpeed",
        "base": 0
    },
    {
        "type": "state",
        "id": "brewingSpeed",
        "base": 0
    },
    {
        "type": "state",
        "id": "alchemySpeed",
        "base": 0
    },
    {
        "type": "state",
        "id": "enhancingSpeed",
        "base": 0
    },
    {
        "type": "slot",
        "id": "miningTool",
        "sort": 0
    },
    {
        "type": "slot",
        "id": "woodcuttingTool",
        "sort": 1
    },
    {
        "type": "slot",
        "id": "foragingTool",
        "sort": 2
    },
    {
        "type": "slot",
        "id": "smithingTool",
        "sort": 3
    },
    {
        "type": "slot",
        "id": "craftingTool",
        "sort": 4
    },
    {
        "type": "slot",
        "id": "tailoringTool",
        "sort": 5
    },
    {
        "type": "slot",
        "id": "cookingTool",
        "sort": 6
    },
    {
        "type": "slot",
        "id": "brewingTool",
        "sort": 7
    },
    {
        "type": "slot",
        "id": "alchemyTool",
        "sort": 8
    },
    {
        "type": "slot",
        "id": "enhancingTool",
        "sort": 9
    },
    {
        "type": "item",
        "itemType": "resource",
        "id": "copperOre",
        "sort": 0
    },
    {
        "type": "item",
        "itemType": "resource",
        "id": "copperIngot",
        "sort": 1
    },
    {
        "type": "item",
        "itemType": "chest",
        "id": "copperMineChest",
        "sort": 0,
        "maxPoints": 1000,
        "loots": [
            {
                "item": "copperOre",
                "chance": 1,
                "min": 10,
                "max": 50
            },
            {
                "item": "copperOre",
                "chance": 0.5,
                "min": 50,
                "max": 100
            },
            {
                "item": "copperIngot",
                "chance": 0.5,
                "min": 1,
                "max": 2
            },
            {
                "item": "copperPickaxe",
                "chance": 0.5,
                "min": 1,
                "max": 1
            },
            {
                "item": "copperMineChest",
                "chance": 0.33,
                "min": 1,
                "max": 1
            }
        ]
    },
    {
        "type": "item",
        "itemType": "equipment",
        "id": "copperPickaxe",
        "sort": 2,
        "slot": "miningTool",
        "effects": [
            {
                "state": "miningSpeed",
                "type": "flat",
                "value": 0.5
            }
        ]
    },
    {
        "type": "item",
        "itemType": "equipment",
        "id": "copperSmithingHammer",
        "sort": 3,
        "slot": "smithingTool",
        "effects": [
            {
                "state": "smithingSpeed",
                "type": "flat",
                "value": 0.5
            }
        ]
    },
    {
        "type": "actionTarget",
        "targetType": "gatheringZone",
        "id": "copperMine",
        "skill": "mining",
        "minLevel": 0,
        "sort": 0,
        "duration": {
            "base": 2000,
            "boosts": [
                {
                    "state": "miningSpeed",
                    "type": "inversePercentage"
                },
                "overLevelSpeedUp"
            ]
        },
        "xp": {
            "base": 5,
            "boosts": []
        },
        "chest": "copperMineChest",
        "chestPoints": {
            "base": 200,
            "boosts": []
        },
        "products": [
            {
                "item": "copperOre",
                "count": 1
            }
        ]
    },
    {
        "type": "actionTarget",
        "targetType": "recipe",
        "id": "copperIngot",
        "skill": "smithing",
        "minLevel": 0,
        "sort": 0,
        "duration": {
            "base": 1000,
            "boosts": [
                {
                    "state": "smithingSpeed",
                    "type": "inversePercentage"
                },
                "overLevelSpeedUp"
            ]
        },
        "xp": {
            "base": 50,
            "boosts": []
        },
        "chest": "copperMineChest",
        "chestPoints": {
            "base": 5,
            "boosts": []
        },
        "ingredients": [
            {
                "item": "copperOre",
                "count": 2
            }
        ],
        "products": [
            {
                "item": "copperIngot",
                "count": 1
            }
        ]
    },
    {
        "type": "actionTarget",
        "targetType": "recipe",
        "id": "copperPickaxe",
        "skill": "smithing",
        "minLevel": 10,
        "sort": 1,
        "duration": {
            "base": 3000,
            "boosts": [
                {
                    "state": "smithingSpeed",
                    "type": "inversePercentage"
                },
                "overLevelSpeedUp"
            ]
        },
        "xp": {
            "base": 5,
            "boosts": []
        },
        "chest": "copperMineChest",
        "chestPoints": {
            "base": 5,
            "boosts": []
        },
        "ingredients": [
            {
                "item": "copperIngot",
                "count": 5
            }
        ],
        "products": [
            {
                "item": "copperPickaxe",
                "count": 1
            }
        ]
    },
    {
        "type": "actionTarget",
        "targetType": "recipe",
        "id": "copperSmithingHammer",
        "skill": "smithing",
        "minLevel": 10,
        "sort": 2,
        "duration": {
            "base": 3000,
            "boosts": [
                {
                    "state": "smithingSpeed",
                    "type": "inversePercentage"
                },
                "overLevelSpeedUp"
            ]
        },
        "xp": {
            "base": 5,
            "boosts": []
        },
        "chest": "copperMineChest",
        "chestPoints": {
            "base": 5,
            "boosts": []
        },
        "ingredients": [
            {
                "item": "copperIngot",
                "count": 5
            }
        ],
        "products": [
            {
                "item": "copperSmithingHammer",
                "count": 1
            }
        ]
    }
]